[
	{
		"id": 0,
		"name": "Renekton",
		"description": "THE BUTCHER OF THE SANDS",
		"price": 4800,
		"isMelee": true,
		"addDate": "2011-01-18",
		"img": "https://img",
		"resource": "fury",
		"abilities": ["Cull the Meek","Ruthless predator","Slice","Dominus"],
		"location":{
			"id": 0,
			"name": "Shurima",
			"evil": false
		}
	},
	{
		"id": 1,
		"name": "Nasus",
		"description": "THE CURATOR OF THE SANDS",
		"price": 1350,
		"isMelee": true,
		"addDate": "2009-10-01",
		"img": "https://img",
		"resource": "mana",
		"abilities": ["Siphoning Strike","Wither","Spirit Fire","Fury of the Sands"],
		"location":{
			"id": 0,
			"name": "Shurima",
			"evil": false
		}
	},
	{
		"id": 2,
		"name": "Malzahar",
		"description": "THE PROPHET OF THE VOID",
		"price": 4800,
		"isMelee": false,
		"addDate": "2010-06-01",
		"img": "https://img",
		"resource": "mana",
		"abilities": ["Call of the Void","Void Swarm","Malefic Visions","Nether Grasp"],
		"location":{
			"id": 1,
			"name": "Void",
			"evil": true
		}
	},
	{
		"id": 3,
		"name": "Darius",
		"description": "THE HAND OF NOXUS",
		"price": 450,
		"isMelee": true,
		"addDate": "2012-05-23",
		"img": "https://img",
		"resoure": "mana",
		"abilities": ["Decimate","Crippling Strike","Apprehend","Noxian Guillotine"],
		"location":{
			"id": 2,
			"name": "Noxus",
			"evil": true
		}
	},
	{
		"id": 4,
		"name": "Teemo",
		"description": "THE SWIFT SCOUT",
		"price": 450,
		"isMelee": false,
		"addDate": "2009-02-21",
		"img": "https://img",
		"resource": "mana",
		"abilities": ["Blinding Dart","Move Quick","Toxic Shot","Noxious Trap"],
		"location":{
			"id": 3,
			"name": "Bandle City",
			"evil": false
		}
	},
	{
		"id": 5,
		"name": "Katarina",
		"description": "THE SINISTER BLADE",
		"price": 3150,
		"isMelee": true,
		"addDate": "2009-09-19",
		"img": "https://img",
		"resource": "manaless",
		"abilities": ["Bouncing Blade","Predaration","Shunpo","Death Lotus"],
		"location":{
			"id": 2,
			"name": "Noxus",
			"evil": true
		}
	},
	{
		"id": 6,
		"name": "Jhin",
		"description": "THE VIRTUOSO",
		"price": 4444,
		"isMelee": false,
		"addDate": "2016-02-01",
		"img": "https://img",
		"resrouce": "mana",
		"abilities": ["Dancing Grenade","Deadly Flourish","Captive Audience","Curtain Call"],
		"location":{
			"id": 4,
			"name": "Ionia",
			"evil": false
		}
	},
	{
		"id": 7,
		"name": "Bard",
		"description": "THE WANDERING CARETAKER",
		"price": 4800,
		"isMelee": false,
		"addDate": "2015-03-12",
		"img": "https://img",
		"resource": "mana",
		"abilities": ["Cosmic Binding","Caretaker's Shrine","Magical Journey","Tempered Fate"],
		"location":{
			"id": 5,
			"name": "Runeterra",
			"evil": false
		}
	},
	{
		"id": 8,
		"name": "Nidalee",
		"description": "THE BESTIAL HUNTRESS",
		"price": 3150,
		"isMelee": false,
		"addDate": "2009-12-17",
		"img": "https://img",
		"resource": "mana",
		"abilities": ["Javelin Toss","Bushwhack","Primal Surge","Aspect of the Cougar"],
		"location":{
			"id": 6,
			"name": "Wilderness",
			"evil": true
		}
	},
	{
		"id": 9,
		"name": "Mordekaiser",
		"description": "THE IRON REVENANT",
		"price": 1350,
		"isMelee": true,
		"addDate": "2010-02-24",
		"img": "https://img",
		"Resource": "shield",
		"abilities": ["Obliterate","Indestructible","Death's Grasp","Realm of Death"],
		"location":{
			"id": 2,
			"name": "Noxus",
			"evil": true
		}
	}
]